odoo/addons/fieldservice_stock_account_analytic/README.rst
odoo/addons/fieldservice_stock_account_analytic/__init__.py
odoo/addons/fieldservice_stock_account_analytic/__manifest__.py
odoo/addons/fieldservice_stock_account_analytic/i18n/de.po
odoo/addons/fieldservice_stock_account_analytic/i18n/es.po
odoo/addons/fieldservice_stock_account_analytic/i18n/es_CL.po
odoo/addons/fieldservice_stock_account_analytic/i18n/fieldservice_stock_account_analytic.pot
odoo/addons/fieldservice_stock_account_analytic/i18n/pt_BR.po
odoo/addons/fieldservice_stock_account_analytic/i18n/pt_PT.po
odoo/addons/fieldservice_stock_account_analytic/models/__init__.py
odoo/addons/fieldservice_stock_account_analytic/models/fsm_order.py
odoo/addons/fieldservice_stock_account_analytic/models/stock_request.py
odoo/addons/fieldservice_stock_account_analytic/readme/CONTRIBUTORS.rst
odoo/addons/fieldservice_stock_account_analytic/readme/DESCRIPTION.rst
odoo/addons/fieldservice_stock_account_analytic/readme/ROADMAP.rst
odoo/addons/fieldservice_stock_account_analytic/readme/USAGE.rst
odoo/addons/fieldservice_stock_account_analytic/static/description/icon.png
odoo/addons/fieldservice_stock_account_analytic/static/description/index.html
odoo12_addon_fieldservice_stock_account_analytic-12.0.1.1.0.dist-info/METADATA
odoo12_addon_fieldservice_stock_account_analytic-12.0.1.1.0.dist-info/WHEEL
odoo12_addon_fieldservice_stock_account_analytic-12.0.1.1.0.dist-info/top_level.txt
odoo12_addon_fieldservice_stock_account_analytic-12.0.1.1.0.dist-info/RECORD
